zhongkui_core-0.1.0-py3.7-nspkg.pth
zhongkui/core/__init__.py
zhongkui/core/corpus.py
zhongkui/core/exception.py
zhongkui/core/file.py
zhongkui/core/parse.py
zhongkui/core/utils.py
zhongkui_core-0.1.0.dist-info/LICENSE
zhongkui_core-0.1.0.dist-info/METADATA
zhongkui_core-0.1.0.dist-info/WHEEL
zhongkui_core-0.1.0.dist-info/namespace_packages.txt
zhongkui_core-0.1.0.dist-info/top_level.txt
zhongkui_core-0.1.0.dist-info/zip-safe
zhongkui_core-0.1.0.dist-info/RECORD
