Metadata-Version: 2.1
Name: zhongkui-core
Version: 0.1.0
Summary: zhongkui core utils package
Home-page: https://git.kongkongss.com/jyk/jyk-time
Author: Yongkang Jiang
Author-email: jyk.kongkong@gmail.com
License: MIT
Platform: UNKNOWN
Classifier: Programming Language :: Python :: 3.7
Classifier: License :: OSI Approved :: MIT License
Classifier: Operating System :: OS Independent
Requires-Python: >=3.7
